{
  "_class": "group",
  "booleanOperation": -1,
  "clippingMaskMode": 0,
  "do_objectID": "F4DAB088-6B03-4356-BC54-E60B11C66C66",
  "exportOptions": {
    "_class": "exportOptions",
    "exportFormats": [
    ],
    "includedLayerIds": [
    ],
    "layerOptions": 0,
    "shouldTrim": false
  },
  "frame": {
    "_class": "rect",
    "constrainProportions": false,
    "height": 284,
    "width": 1440,
    "x": 0,
    "y": 840
  },
  "groupLayout": {
    "_class": "MSImmutableFreeformGroupLayout"
  },
  "hasClickThrough": false,
  "hasClippingMask": false,
  "isFixedToViewport": false,
  "isFlippedHorizontal": false,
  "isFlippedVertical": false,
  "isLocked": false,
  "isVisible": true,
  "layerListExpandedType": 0,
  "layers": [
    {
      "class": "rectangle",
      "id": "ECAFB2B3-F604-4085-BC0B-2994DD7B36B2"
    },
    {
      "class": "group",
      "id": "5197707B-2C8B-49A8-A0E4-B1C71B321EBF"
    },
    {
      "class": "group",
      "id": "7EAC3942-1681-46D4-84D2-22A6E49B4EA5"
    }
  ],
  "name": "Block - 2",
  "nameIsFixed": true,
  "resizingConstraint": 15,
  "resizingType": 0,
  "rotation": 0,
  "shouldBreakMaskChain": false,
  "style": {
    "_class": "style",
    "endMarkerType": 0,
    "miterLimit": 10,
    "startMarkerType": 0,
    "windingRule": 1
  }
}