{
  "_class": "shapeGroup",
  "booleanOperation": 0,
  "clippingMaskMode": 0,
  "do_objectID": "B990173B-31CF-431F-BC03-6196EEF6E571",
  "exportOptions": {
    "_class": "exportOptions",
    "exportFormats": [
    ],
    "includedLayerIds": [
    ],
    "layerOptions": 0,
    "shouldTrim": false
  },
  "frame": {
    "_class": "rect",
    "constrainProportions": false,
    "height": 21.00000000000006,
    "width": 18,
    "x": 3,
    "y": 1.5
  },
  "groupLayout": {
    "_class": "MSImmutableFreeformGroupLayout"
  },
  "hasClickThrough": false,
  "hasClippingMask": true,
  "isFixedToViewport": false,
  "isFlippedHorizontal": false,
  "isFlippedVertical": false,
  "isLocked": false,
  "isVisible": true,
  "layerListExpandedType": 0,
  "layers": [
    {
      "class": "shapePath",
      "id": "82CB9525-A2AD-416D-953D-658F36AE4035"
    },
    {
      "class": "shapePath",
      "id": "10016E56-120D-4B86-A154-EDDA6269ADB3"
    },
    {
      "class": "shapePath",
      "id": "6932F7C1-7A4A-40E4-8E86-8D1069834E3C"
    }
  ],
  "name": "↳Color",
  "nameIsFixed": true,
  "resizingConstraint": 63,
  "resizingType": 0,
  "rotation": 0,
  "sharedStyleID": "7506F2DB-3127-45F1-BD79-82516071B13C",
  "shouldBreakMaskChain": false,
  "style": {
    "_class": "style",
    "do_objectID": "5A509DC8-9969-4094-A51A-0F0B7D216412",
    "endMarkerType": 0,
    "fills": [
      {
        "_class": "fill",
        "color": {
          "_class": "color",
          "alpha": 1,
          "blue": 1,
          "green": 0.46168681755303,
          "red": 0
        },
        "fillType": 0,
        "isEnabled": true,
        "noiseIndex": 0,
        "noiseIntensity": 0,
        "patternFillType": 1,
        "patternTileScale": 1
      }
    ],
    "miterLimit": 10,
    "startMarkerType": 0,
    "windingRule": 1
  },
  "windingRule": 1
}